linggapy/__init__.py
linggapy/corrector/__init__.py
linggapy/corrector/corrector.py
linggapy/data/root-words.txt
linggapy/data/stop-words.txt
linggapy/data/word-articles.txt
linggapy/data/words.txt
linggapy/normalizer/__init__.py
linggapy/normalizer/normalizer.py
linggapy/stemmer/__init__.py
linggapy/stemmer/stemmer.py
linggapy/stemmer/disambiguator/__init__.py
linggapy/stemmer/disambiguator/confix.py
linggapy/stemmer/disambiguator/disambiguator.py
linggapy/stemmer/disambiguator/infix.py
linggapy/stemmer/disambiguator/prefix.py
linggapy/stemmer/disambiguator/suffix.py
linggapy/utils/__init__.py
linggapy/utils/cacher.py
linggapy/utils/loader.py
linggapy/utils/logger.py
tests/__init__.py
tests/test_stemmer.py
linggapy-0.3.0.dist-info/LICENSE
linggapy-0.3.0.dist-info/METADATA
linggapy-0.3.0.dist-info/WHEEL
linggapy-0.3.0.dist-info/top_level.txt
linggapy-0.3.0.dist-info/RECORD
